parxyval/__init__.py
parxyval/cli/__init__.py
parxyval/cli/commands/__init__.py
parxyval/cli/commands/download.py
parxyval/cli/commands/evaluate.py
parxyval/cli/commands/parse.py
parxyval/cli/main.py
parxyval/data_handler/__init__.py
parxyval/data_handler/doclaynet_to_parxy.py
parxyval/evaluation/__init__.py
parxyval/evaluation/convert_to_pdf.py
parxyval/evaluation/factory.py
parxyval/evaluation/layout_metrics.py
parxyval/evaluation/text_metrics.py
parxyval/evaluation/utils.py
parxyval/models/__init__.py
parxyval/models/dataset.py
parxyval/py.typed
parxyval-0.1.1.dist-info/WHEEL
parxyval-0.1.1.dist-info/entry_points.txt
parxyval-0.1.1.dist-info/METADATA
parxyval-0.1.1.dist-info/RECORD
