Metadata-Version: 2.4
Name: parxyval
Version: 0.1.1
Summary: An evaluation framework for document parsing.
Keywords: parxy,evaluation,evaluation-framework,convert,document,document-parsing,parser-benchmark,pdf,docx,html,markdown,layout model,rag,llm,document-performance-monitoring,document-ai,text-extraction,data-quality,rag,parsing-tools
Author: Alessio Vertemati
Author-email: Alessio Vertemati <alessio@oneofftech.xyz>
License-Expression: MIT
Classifier: Operating System :: MacOS :: MacOS X
Classifier: Operating System :: POSIX :: Linux
Classifier: Operating System :: Microsoft :: Windows
Classifier: Development Status :: 4 - Beta
Classifier: Intended Audience :: Developers
Classifier: Intended Audience :: Science/Research
Classifier: Topic :: Scientific/Engineering :: Artificial Intelligence
Classifier: Programming Language :: Python :: 3
Classifier: License :: OSI Approved :: MIT License
Requires-Dist: datasets>=4.1.1
Requires-Dist: nltk>=3.9.2
Requires-Dist: pandas>=2.3.3
Requires-Dist: parxy[all]>=0.10.0
Requires-Dist: pydantic>=2.11.9
Requires-Dist: pydantic-settings>=2.11.0
Requires-Dist: pymupdf>=1.26.4
Requires-Dist: python-dotenv>=1.1.1
Requires-Dist: rich>=14.1.0
Requires-Dist: tqdm>=4.67.1
Requires-Dist: typer>=0.19.2
Requires-Python: >=3.12, <4.0
Project-URL: homepage, https://github.com/OneOffTech/parxyval
Project-URL: issues, https://github.com/OneOffTech/parxyval/issues
Project-URL: repository, https://github.com/OneOffTech/parxyval
